calcurse_load/__init__.py
calcurse_load/__main__.py
calcurse_load/calcurse.py
calcurse_load/log.py
calcurse_load/py.typed
calcurse_load/ext/__init__.py
calcurse_load/ext/abstract.py
calcurse_load/ext/all.py
calcurse_load/ext/gcal.py
calcurse_load/ext/todotxt.py
calcurse_load/ext/utils.py
gcal_index/__init__.py
gcal_index/__main__.py
calcurse_load-0.1.1.dist-info/LICENSE
calcurse_load-0.1.1.dist-info/METADATA
calcurse_load-0.1.1.dist-info/WHEEL
calcurse_load-0.1.1.dist-info/entry_points.txt
calcurse_load-0.1.1.dist-info/top_level.txt
calcurse_load-0.1.1.dist-info/RECORD
