Metadata-Version: 2.1
Name: calcurse-load
Version: 0.1.1
Summary: Sources events for calcurse from Google Calendar and todo.txt
Home-page: https://github.com/seanbreckenridge/calcurse_load
Author: Sean Breckenridge
Author-email: "seanbrecke@gmail.com"
License: MIT
Keywords: calendar todo google
Classifier: License :: OSI Approved :: MIT License
Classifier: Programming Language :: Python :: 3
Classifier: Programming Language :: Python :: 3 :: Only
Classifier: Programming Language :: Python :: 3.8
Classifier: Programming Language :: Python :: 3.9
Classifier: Programming Language :: Python :: 3.10
Classifier: Programming Language :: Python :: 3.11
Classifier: Programming Language :: Python :: 3.12
Requires-Python: >=3.8
License-File: LICENSE
Requires-Dist: click
Requires-Dist: cssselect
Requires-Dist: gcsa >=0.4.0
Requires-Dist: logzero
Requires-Dist: lxml
Provides-Extra: testing
Requires-Dist: flake8 ; extra == 'testing'
Requires-Dist: mypy ; extra == 'testing'
Requires-Dist: pytest ; extra == 'testing'
